reqt/__init__.py
reqt/helpers.py
reqt/tests/__init__.py
reqt/tests/test_advanced.py
reqt/tests/test_basic.py
reqt-1.0.3.dist-info/LICENSE
reqt-1.0.3.dist-info/METADATA
reqt-1.0.3.dist-info/WHEEL
reqt-1.0.3.dist-info/top_level.txt
reqt-1.0.3.dist-info/RECORD
