Metadata-Version: 2.1
Name: reqt
Version: 1.0.3
Summary: Reqt Package
Home-page: https://github.com/melihcolpan/reqt
Author: Melih Colpan
Author-email: melihcolpan1@gmail.com
License: UNKNOWN
Platform: UNKNOWN
Requires-Dist: aiohttp
